mirtop/__init__.py
mirtop/command_line.py
mirtop/install.py
mirtop/version.py
mirtop/bam/__init__.py
mirtop/bam/bam.py
mirtop/bam/filter.py
mirtop/exporter/__init__.py
mirtop/exporter/fasta.py
mirtop/exporter/isomirs.py
mirtop/exporter/seqbuster.py
mirtop/exporter/vcf.py
mirtop/gff/__init__.py
mirtop/gff/body.py
mirtop/gff/check.py
mirtop/gff/classgff.py
mirtop/gff/compare.py
mirtop/gff/convert.py
mirtop/gff/gff_versions.py
mirtop/gff/header.py
mirtop/gff/merge.py
mirtop/gff/query.py
mirtop/gff/read.py
mirtop/gff/stats.py
mirtop/gff/update.py
mirtop/gff/validator.py
mirtop/importer/__init__.py
mirtop/importer/isomirsea.py
mirtop/importer/manatee.py
mirtop/importer/optimir.py
mirtop/importer/prost.py
mirtop/importer/seqbuster.py
mirtop/importer/srnabench.py
mirtop/libs/__init__.py
mirtop/libs/config.py
mirtop/libs/do.py
mirtop/libs/fastq.py
mirtop/libs/logger.py
mirtop/libs/parse.py
mirtop/libs/read.py
mirtop/libs/simulator.py
mirtop/libs/spikeins.py
mirtop/libs/sql.py
mirtop/libs/utils.py
mirtop/mirna/__init__.py
mirtop/mirna/annotate.py
mirtop/mirna/fasta.py
mirtop/mirna/keys.py
mirtop/mirna/mapper.py
mirtop/mirna/mintplates.py
mirtop/mirna/realign.py
mirtop/mirna/snps.py
mirtop/sql/__init__.py
mirtop/sql/sql.py
mirtop-0.4.30.dist-info/licenses/LICENSE
mirtop-0.4.30.dist-info/METADATA
mirtop-0.4.30.dist-info/WHEEL
mirtop-0.4.30.dist-info/entry_points.txt
mirtop-0.4.30.dist-info/top_level.txt
mirtop-0.4.30.dist-info/RECORD
