Metadata-Version: 2.4
Name: mirtop
Version: 0.4.30
Summary: Small RNA-seq annotation
Home-page: http://github.com/mirtop/mirtop
Author: Lorena Pantano
Author-email: lorena.pantano@gmail.com
License: MIT
Keywords: RNA-seq miRNA isomiRs annotation
Classifier: License :: OSI Approved :: MIT License
Classifier: Programming Language :: Python :: 2.7
Classifier: Programming Language :: Python :: 3
Classifier: Topic :: Scientific/Engineering :: Bio-Informatics
License-File: LICENSE
Dynamic: author
Dynamic: author-email
Dynamic: classifier
Dynamic: description
Dynamic: description-content-type
Dynamic: home-page
Dynamic: keywords
Dynamic: license
Dynamic: license-file
Dynamic: summary
